{"poster_size": 23887872, "doclen": 448, "figlen": 5645176, "section": {"0": {"xy": [1783, 77, 3347, 141], "panel_size": 471927, "panel_aspectRatio": 23.73758865248227, "category": "Title", "figures": 0, "textlen": 0, "fig_size": 0, "title": "Support Recovery for Orthogonal Matching Pursuit: Upper and Lower bounds", "textRatio": 0.0, "figRatio": 0.0}, "1": {"xy": [152, 470, 1550, 453], "panel_size": 702150, "panel_aspectRatio": 3.4216335540838854, "category": "Introduction", "figures": 0, "textlen": 39, "fig_size": 0, "title": "Abstract", "textRatio": 0.08705357142857142, "figRatio": 0.0}, "3": {"xy": [140, 944, 1584, 692], "panel_size": 1096128, "panel_aspectRatio": 2.2890173410404624, "category": "Introduction", "figures": 3, "textlen": 16, "fig_size": 547601, "title": "Introduction", "4": {"fig_size": 181458, "fig_aspectRatio": 7.751633986928105, "fig_size_poster": 0.7487373737373737}, "6": {"fig_size": 239575, "fig_aspectRatio": 7.822857142857143, "fig_size_poster": 0.8642676767676768}, "8": {"fig_size": 126568, "fig_aspectRatio": 11.701923076923077, "fig_size_poster": 0.7683080808080808}, "textRatio": 0.03571428571428571, "figRatio": 0.09700335295126317}, "9": {"xy": [135, 1658, 1592, 259], "panel_size": 412328, "panel_aspectRatio": 6.146718146718147, "category": "Introduction", "figures": 0, "textlen": 15, "fig_size": 0, "title": "Goals of SLR", "textRatio": 0.033482142857142856, "figRatio": 0.0}, "11": {"xy": [135, 1950, 1559, 494], "panel_size": 770146, "panel_aspectRatio": 3.1558704453441297, "category": "Introduction", "figures": 0, "textlen": 36, "fig_size": 0, "title": "Existing SLR algorithms", "textRatio": 0.08035714285714286, "figRatio": 0.0}, "15": {"xy": [135, 2462, 1552, 669], "panel_size": 1038288, "panel_aspectRatio": 2.319880418535127, "category": "Introduction", "figures": 0, "textlen": 83, "fig_size": 0, "title": "Orthogonal Matching Pursuit", "textRatio": 0.18526785714285715, "figRatio": 0.0}, "17": {"xy": [1813, 458, 1620, 642], "panel_size": 1040040, "panel_aspectRatio": 2.5233644859813085, "category": "Method", "figures": 2, "textlen": 13, "fig_size": 369408, "title": "Upper bound on Generalization Error", "18": {"fig_size": 199056, "fig_aspectRatio": 9.734265734265735, "fig_size_poster": 0.8592592592592593}, "24": {"fig_size": 170352, "fig_aspectRatio": 7.0, "fig_size_poster": 0.674074074074074}, "textRatio": 0.029017857142857144, "figRatio": 0.06543781805917123}, "25": {"xy": [1829, 1129, 1575, 1008], "panel_size": 1587600, "panel_aspectRatio": 1.5625, "category": "Method", "figures": 2, "textlen": 36, "fig_size": 551278, "title": "Support Recovery upper bound", "28": {"fig_size": 315948, "fig_aspectRatio": 6.185840707964601, "fig_size_poster": 0.8876190476190476}, "31": {"fig_size": 235330, "fig_aspectRatio": 5.767326732673268, "fig_size_poster": 0.7396825396825397}, "textRatio": 0.08035714285714286, "figRatio": 0.0976547055397387}, "32": {"xy": [1835, 2160, 1586, 1178], "panel_size": 1868308, "panel_aspectRatio": 1.3463497453310695, "category": "Discussion", "figures": 1, "textlen": 61, "fig_size": 1154434, "title": "Remarks and Comparison", "34": {"fig_size": 1154434, "fig_aspectRatio": 2.009234828496042, "fig_size_poster": 0.9602774274905422}, "textRatio": 0.13616071428571427, "figRatio": 0.20449920427635915}, "35": {"xy": [3500, 462, 1519, 784], "panel_size": 1190896, "panel_aspectRatio": 1.9375, "category": "Result", "figures": 2, "textlen": 24, "fig_size": 605779, "title": "Results for Gaussian ensemble", "37": {"fig_size": 235984, "fig_aspectRatio": 6.142857142857143, "fig_size_poster": 0.7926267281105991}, "38": {"fig_size": 369795, "fig_aspectRatio": 4.819494584837545, "fig_size_poster": 0.8788676761026991}, "textRatio": 0.05357142857142857, "figRatio": 0.10730914324017533}, "39": {"xy": [3500, 1281, 1565, 1119], "panel_size": 1751235, "panel_aspectRatio": 1.3985701519213583, "category": "Method", "figures": 4, "textlen": 13, "fig_size": 847732, "title": "Lower bound instance construction", "41": {"fig_size": 214799, "fig_aspectRatio": 7.520710059171598, "fig_size_poster": 0.8121405750798723}, "42": {"fig_size": 82289, "fig_aspectRatio": 16.323943661971832, "fig_size_poster": 0.7405750798722045}, "43": {"fig_size": 195228, "fig_aspectRatio": 11.204545454545455, "fig_size_poster": 0.9450479233226837}, "44": {"fig_size": 355416, "fig_aspectRatio": 1.4103585657370519, "fig_size_poster": 0.4523961661341853}, "textRatio": 0.029017857142857144, "figRatio": 0.1501692772731975}, "45": {"xy": [3510, 2420, 1685, 950], "panel_size": 1600750, "panel_aspectRatio": 1.7736842105263158, "category": "Result", "figures": 2, "textlen": 24, "fig_size": 604885, "title": "Lower bound: Noiseless case", "47": {"fig_size": 268155, "fig_aspectRatio": 8.559322033898304, "fig_size_poster": 0.8991097922848664}, "49": {"fig_size": 336730, "fig_aspectRatio": 6.771300448430493, "fig_size_poster": 0.8961424332344213}, "textRatio": 0.05357142857142857, "figRatio": 0.10715077793854434}, "52": {"xy": [5171, 467, 1675, 956], "panel_size": 1601300, "panel_aspectRatio": 1.752092050209205, "category": "Result", "figures": 1, "textlen": 44, "fig_size": 964059, "title": "Simulations", "54": {"fig_size": 964059, "fig_aspectRatio": 2.406003159557662, "fig_size_poster": 0.9092537313432836}, "textRatio": 0.09821428571428571, "figRatio": 0.1707757207215506}, "56": {"xy": [5208, 1446, 1577, 294], "panel_size": 463638, "panel_aspectRatio": 5.363945578231292, "category": "Result", "figures": 0, "textlen": 44, "fig_size": 0, "title": "Conclusion", "textRatio": 0.09821428571428571, "figRatio": 0.0}}}