{"poster_size": 8036464, "doclen": 462, "figlen": 3180788, "section": {"0": {"xy": [291, 7, 2803, 231], "panel_size": 647493, "panel_aspectRatio": 12.134199134199134, "category": "Title", "figures": 0, "textlen": 0, "fig_size": 0, "title": "REGRETBOUNDS FOR META BAYESIAN OPTIMIZATION WITH AN UNKNOWN GAUSSIANPROCESS PRIOR", "textRatio": 0.0, "figRatio": 0.0}, "1": {"xy": [788, 138, 1806, 77], "panel_size": 139062, "panel_aspectRatio": 23.454545454545453, "category": "Title", "figures": 0, "textlen": 0, "fig_size": 0, "title": "ZiWANG\uff0cBEOMJOON KIM\uff0cLESLIE PACK KAELBLING ziw, beomjoon,lpk @ mit.edu\n(equal contribution)", "textRatio": 0.0, "figRatio": 0.0}, "2": {"xy": [31, 260, 820, 246], "panel_size": 201720, "panel_aspectRatio": 3.3333333333333335, "category": "Introduction", "figures": 0, "textlen": 35, "fig_size": 0, "title": "MAIN CONTRIBUTIONS\n", "textRatio": 0.07575757575757576, "figRatio": 0.0}, "4": {"xy": [35, 519, 818, 750], "panel_size": 613500, "panel_aspectRatio": 1.0906666666666667, "category": "Method", "figures": 2, "textlen": 78, "fig_size": 172965, "title": "BAYESIAN OPTIMIZATION\n", "6": {"fig_size": 137925, "fig_aspectRatio": 2.7244444444444444, "fig_size_poster": 0.7493887530562348}, "7": {"fig_size": 35040, "fig_aspectRatio": 0.730593607305936, "fig_size_poster": 0.19559902200489}, "textRatio": 0.16883116883116883, "figRatio": 0.05437803462538214}, "8": {"xy": [34, 1285, 819, 705], "panel_size": 577395, "panel_aspectRatio": 1.1617021276595745, "category": "Method", "figures": 3, "textlen": 8, "fig_size": 432606, "title": "OUR MODEL", "9": {"fig_size": 385032, "fig_aspectRatio": 1.6168032786885247, "fig_size_poster": 0.9633699633699634}, "12": {"fig_size": 21114, "fig_aspectRatio": 8.117647058823529, "fig_size_poster": 0.5054945054945055}, "14": {"fig_size": 26460, "fig_aspectRatio": 11.020408163265307, "fig_size_poster": 0.6593406593406593}, "textRatio": 0.017316017316017316, "figRatio": 0.1360059205454749}, "15": {"xy": [29, 1998, 824, 360], "panel_size": 296640, "panel_aspectRatio": 2.2888888888888888, "category": "Method", "figures": 1, "textlen": 0, "fig_size": 198290, "title": "GAUSSIAN PROCESSES", "16": {"fig_size": 198290, "fig_aspectRatio": 3.147410358565737, "fig_size_poster": 0.9587378640776699}, "textRatio": 0.0, "figRatio": 0.062339898163599715}, "17": {"xy": [864, 256, 1643, 447], "panel_size": 734421, "panel_aspectRatio": 3.675615212527964, "category": "Result", "figures": 2, "textlen": 61, "fig_size": 302736, "title": "MAIN IDEA: USE THE PAST EXPERIENCE TO ESTIMATE THE PRIOR OF f", "18": {"fig_size": 263056, "fig_aspectRatio": 2.4451219512195124, "fig_size_poster": 0.4881314668289714}, "20": {"fig_size": 39680, "fig_aspectRatio": 9.6875, "fig_size_poster": 0.37735849056603776}, "textRatio": 0.13203463203463203, "figRatio": 0.09517641540398165}, "22": {"xy": [864, 716, 1652, 953], "panel_size": 1574356, "panel_aspectRatio": 1.7334732423924448, "category": "Method", "figures": 10, "textlen": 115, "fig_size": 697153, "title": "ESTIMATE THE PRIOR GP(u,k) AND POSTERIOR GP(ut.kt): DISCRETE AND CONTINUOUS CASES", "24": {"fig_size": 198000, "fig_aspectRatio": 9.54861111111111, "fig_size_poster": 0.8323244552058111}, "26": {"fig_size": 79110, "fig_aspectRatio": 0.9215017064846417, "fig_size_poster": 0.16343825665859565}, "27": {"fig_size": 78976, "fig_aspectRatio": 19.28125, "fig_size_poster": 0.7469733656174334}, "28": {"fig_size": 23300, "fig_aspectRatio": 9.32, "fig_size_poster": 0.2820823244552058}, "29": {"fig_size": 28273, "fig_aspectRatio": 11.775510204081632, "fig_size_poster": 0.349273607748184}, "32": {"fig_size": 20930, "fig_aspectRatio": 17.085714285714285, "fig_size_poster": 0.3619854721549637}, "33": {"fig_size": 35137, "fig_aspectRatio": 20.902439024390244, "fig_size_poster": 0.5187651331719129}, "36": {"fig_size": 9765, "fig_aspectRatio": 7.9714285714285715, "fig_size_poster": 0.16888619854721548}, "37": {"fig_size": 24366, "fig_aspectRatio": 25.35483870967742, "fig_size_poster": 0.47578692493946734}, "44": {"fig_size": 199296, "fig_aspectRatio": 12.1640625, "fig_size_poster": 0.9424939467312349}, "textRatio": 0.24891774891774893, "figRatio": 0.21917619156007884}, "45": {"xy": [862, 1681, 1641, 661], "panel_size": 1084701, "panel_aspectRatio": 2.4826021180030255, "category": "Method", "figures": 4, "textlen": 99, "fig_size": 434474, "title": "NEAR ZERO REGRET BOUNDS FOR BO WITH THE ESTIMATED PRIOR AND POSTERIOR", "47": {"fig_size": 197284, "fig_aspectRatio": 6.6686046511627906, "fig_size_poster": 0.6989640463132236}, "50": {"fig_size": 180728, "fig_aspectRatio": 13.431034482758621, "fig_size_poster": 0.9494210847044485}, "51": {"fig_size": 40748, "fig_aspectRatio": 10.950819672131148, "fig_size_poster": 0.40706886045094454}, "54": {"fig_size": 15714, "fig_aspectRatio": 5.388888888888889, "fig_size_poster": 0.1773308957952468}, "textRatio": 0.21428571428571427, "figRatio": 0.13659319640290393}, "55": {"xy": [2517, 271, 831, 1694], "panel_size": 1407714, "panel_aspectRatio": 0.49055489964580873, "category": "Result", "figures": 7, "textlen": 66, "fig_size": 942564, "title": "EXPERIMENTS", "57": {"fig_size": 254794, "fig_aspectRatio": 1.7460732984293195, "fig_size_poster": 0.802647412755716}, "58": {"fig_size": 118104, "fig_aspectRatio": 1.347972972972973, "fig_size_poster": 0.48014440433212996}, "59": {"fig_size": 110408, "fig_aspectRatio": 1.260135135135135, "fig_size_poster": 0.44885679903730447}, "61": {"fig_size": 118008, "fig_aspectRatio": 1.3288590604026846, "fig_size_poster": 0.47653429602888087}, "62": {"fig_size": 110035, "fig_aspectRatio": 1.264406779661017, "fig_size_poster": 0.44885679903730447}, "64": {"fig_size": 120000, "fig_aspectRatio": 1.3333333333333333, "fig_size_poster": 0.4813477737665463}, "65": {"fig_size": 111215, "fig_aspectRatio": 1.2779661016949153, "fig_size_poster": 0.4536702767749699}, "textRatio": 0.14285714285714285, "figRatio": 0.2963303432985788}}}