{"poster_size": 4478976, "doclen": 371, "figlen": 1607374, "section": {"1": {"xy": [378, 44, 1863, 115], "panel_size": 214245, "panel_aspectRatio": 16.2, "category": "Title", "figures": 0, "textlen": 0, "fig_size": 0, "title": "Portfolio Management Using Deep Q Learning", "textRatio": 0.0, "figRatio": 0.0}, "2": {"xy": [23, 328, 903, 213], "panel_size": 192339, "panel_aspectRatio": 4.23943661971831, "category": "Introduction", "figures": 0, "textlen": 52, "fig_size": 0, "title": "Predicting ", "textRatio": 0.14016172506738545, "figRatio": 0.0}, "4": {"xy": [20, 563, 902, 170], "panel_size": 153340, "panel_aspectRatio": 5.305882352941176, "category": "Method", "figures": 0, "textlen": 38, "fig_size": 0, "title": "Data", "textRatio": 0.10242587601078167, "figRatio": 0.0}, "6": {"xy": [18, 753, 909, 173], "panel_size": 157257, "panel_aspectRatio": 5.254335260115607, "category": "Method", "figures": 0, "textlen": 34, "fig_size": 0, "title": "Features", "textRatio": 0.09164420485175202, "figRatio": 0.0}, "8": {"xy": [18, 947, 909, 286], "panel_size": 259974, "panel_aspectRatio": 3.1783216783216783, "category": "Method", "figures": 0, "textlen": 93, "fig_size": 0, "title": "Models", "textRatio": 0.25067385444743934, "figRatio": 0.0}, "11": {"xy": [945, 328, 905, 821], "panel_size": 743005, "panel_aspectRatio": 1.1023142509135202, "category": "Method", "figures": 2, "textlen": 0, "fig_size": 695682, "title": "", "12": {"fig_size": 393807, "fig_aspectRatio": 1.970917225950783, "fig_size_poster": 0.9734806629834254}, "13": {"fig_size": 301875, "fig_aspectRatio": 2.536231884057971, "fig_size_poster": 0.9668508287292817}, "textRatio": 0.0, "figRatio": 0.432806552799784}, "14": {"xy": [1871, 330, 700, 1391], "panel_size": 973700, "panel_aspectRatio": 0.503235082674335, "category": "Method", "figures": 3, "textlen": 0, "fig_size": 911692, "title": "", "15": {"fig_size": 301002, "fig_aspectRatio": 1.5407239819004526, "fig_size_poster": 0.9728571428571429}, "16": {"fig_size": 298350, "fig_aspectRatio": 1.5271493212669682, "fig_size_poster": 0.9642857142857143}, "17": {"fig_size": 312340, "fig_aspectRatio": 1.4760869565217392, "fig_size_poster": 0.97}, "textRatio": 0.0, "figRatio": 0.567193447200216}, "18": {"xy": [25, 1270, 900, 165], "panel_size": 148500, "panel_aspectRatio": 5.454545454545454, "category": "Result", "figures": 0, "textlen": 37, "fig_size": 0, "title": "Results", "textRatio": 0.09973045822102426, "figRatio": 0.0}, "20": {"xy": [22, 1472, 898, 226], "panel_size": 202948, "panel_aspectRatio": 3.9734513274336285, "category": "Discussion", "figures": 0, "textlen": 54, "fig_size": 0, "title": "Future", "textRatio": 0.14555256064690028, "figRatio": 0.0}, "22": {"xy": [952, 1163, 900, 239], "panel_size": 215100, "panel_aspectRatio": 3.7656903765690375, "category": "Discussion", "figures": 0, "textlen": 63, "fig_size": 0, "title": "Discussion", "textRatio": 0.16981132075471697, "figRatio": 0.0}}}