{"poster_size": 4478976, "doclen": 206, "figlen": 1324728, "section": {"1": {"xy": [54, 53, 2497, 110], "panel_size": 274670, "panel_aspectRatio": 22.7, "category": "Title", "figures": 0, "textlen": 0, "fig_size": 0, "title": "Pileup Subtraction and Jet Energy Prediction Using Machine Learning", "textRatio": 0.0, "figRatio": 0.0}, "2": {"xy": [35, 356, 671, 682], "panel_size": 457622, "panel_aspectRatio": 0.9838709677419355, "category": "Introduction", "figures": 1, "textlen": 67, "fig_size": 195650, "title": "Overview", "4": {"fig_size": 195650, "fig_aspectRatio": 1.8523076923076922, "fig_size_poster": 0.8971684053651267}, "textRatio": 0.32524271844660196, "figRatio": 0.1476906957503729}, "5": {"xy": [40, 1066, 672, 634], "panel_size": 426048, "panel_aspectRatio": 1.0599369085173502, "category": "Method", "figures": 2, "textlen": 0, "fig_size": 334190, "title": "Features", "6": {"fig_size": 151200, "fig_aspectRatio": 1.8229166666666667, "fig_size_poster": 0.78125}, "8": {"fig_size": 182990, "fig_aspectRatio": 2.1758620689655173, "fig_size_poster": 0.9389880952380952}, "textRatio": 0.0, "figRatio": 0.2522706548061187}, "9": {"xy": [745, 359, 879, 463], "panel_size": 406977, "panel_aspectRatio": 1.898488120950324, "category": "Method", "figures": 1, "textlen": 45, "fig_size": 99008, "title": "Current method and Baseline", "11": {"fig_size": 99008, "fig_aspectRatio": 2.0271493212669682, "fig_size_poster": 0.5096700796359499}, "textRatio": 0.21844660194174756, "figRatio": 0.07473836138437476}, "12": {"xy": [741, 855, 887, 840], "panel_size": 745080, "panel_aspectRatio": 1.055952380952381, "category": "Method", "figures": 0, "textlen": 94, "fig_size": 0, "title": "Models", "textRatio": 0.4563106796116505, "figRatio": 0.0}, "15": {"xy": [1740, 355, 798, 1104], "panel_size": 880992, "panel_aspectRatio": 0.7228260869565217, "category": "Result", "figures": 2, "textlen": 0, "fig_size": 695880, "title": "III. Results", "16": {"fig_size": 365400, "fig_aspectRatio": 1.3409961685823755, "fig_size_poster": 0.8771929824561403}, "17": {"fig_size": 330480, "fig_aspectRatio": 1.5686274509803921, "fig_size_poster": 0.9022556390977443}, "textRatio": 0.0, "figRatio": 0.5253002880591336}}}