{"poster_size": 4219776, "doclen": 416, "figlen": 1589785, "section": {"1": {"xy": [334, 27, 2057, 111], "panel_size": 228327, "panel_aspectRatio": 18.53153153153153, "category": "Title", "figures": 0, "textlen": 0, "fig_size": 0, "title": "Robust Streaming Video Traffic Classification", "textRatio": 0.0, "figRatio": 0.0}, "2": {"xy": [10, 269, 646, 337], "panel_size": 217702, "panel_aspectRatio": 1.916913946587537, "category": "Introduction", "figures": 0, "textlen": 0, "fig_size": 0, "title": "Background", "textRatio": 0.0, "figRatio": 0.0}, "3": {"xy": [4, 619, 658, 993], "panel_size": 653394, "panel_aspectRatio": 0.6626384692849949, "category": "Method", "figures": 1, "textlen": 147, "fig_size": 92075, "title": "Methods", "6": {"fig_size": 92075, "fig_aspectRatio": 4.379310344827586, "fig_size_poster": 0.9650455927051672}, "textRatio": 0.35336538461538464, "figRatio": 0.05791663652632274}, "8": {"xy": [664, 267, 637, 1360], "panel_size": 866320, "panel_aspectRatio": 0.46838235294117647, "category": "Method", "figures": 2, "textlen": 99, "fig_size": 489294, "title": "Features", "10": {"fig_size": 216315, "fig_aspectRatio": 1.1327231121281465, "fig_size_poster": 0.7770800627943485}, "12": {"fig_size": 272979, "fig_aspectRatio": 1.4036281179138321, "fig_size_poster": 0.9717425431711146}, "textRatio": 0.23798076923076922, "figRatio": 0.3077736926691345}, "13": {"xy": [1309, 265, 633, 1351], "panel_size": 855183, "panel_aspectRatio": 0.4685418208734271, "category": "Result", "figures": 2, "textlen": 85, "fig_size": 530792, "title": "Supervised Learning Results", "15": {"fig_size": 277412, "fig_aspectRatio": 1.3946188340807175, "fig_size_poster": 0.9826224328593997}, "17": {"fig_size": 253380, "fig_aspectRatio": 1.5073170731707317, "fig_size_poster": 0.976303317535545}, "textRatio": 0.20432692307692307, "figRatio": 0.33387659337583386}, "18": {"xy": [1952, 260, 632, 1346], "panel_size": 850672, "panel_aspectRatio": 0.46953937592867756, "category": "Result", "figures": 2, "textlen": 85, "fig_size": 477624, "title": "Unsupervised Learning Results", "20": {"fig_size": 242400, "fig_aspectRatio": 1.4851485148514851, "fig_size_poster": 0.9493670886075949}, "22": {"fig_size": 235224, "fig_aspectRatio": 1.5, "fig_size_poster": 0.939873417721519}, "textRatio": 0.20432692307692307, "figRatio": 0.3004330774287089}}}