{"poster_size": 8018220, "doclen": 494, "figlen": 1075486, "section": {"0": {"xy": [917, 54, 1686, 107], "panel_size": 180402, "panel_aspectRatio": 15.757009345794392, "category": "Title", "figures": 0, "textlen": 0, "fig_size": 0, "title": "Material Synthesis Techniques from a Data-driven Perspective", "textRatio": 0.0, "figRatio": 0.0}, "1": {"xy": [84, 456, 862, 962], "panel_size": 829244, "panel_aspectRatio": 0.896049896049896, "category": "Introduction", "figures": 0, "textlen": 95, "fig_size": 0, "title": "Introduction", "textRatio": 0.19230769230769232, "figRatio": 0.0}, "3": {"xy": [87, 1431, 859, 352], "panel_size": 302368, "panel_aspectRatio": 2.440340909090909, "category": "Method", "figures": 0, "textlen": 37, "fig_size": 0, "title": "Dataset", "textRatio": 0.07489878542510121, "figRatio": 0.0}, "5": {"xy": [87, 1795, 847, 548], "panel_size": 464156, "panel_aspectRatio": 1.5456204379562044, "category": "Method", "figures": 0, "textlen": 47, "fig_size": 0, "title": "Features", "textRatio": 0.0951417004048583, "figRatio": 0.0}, "7": {"xy": [968, 454, 1501, 812], "panel_size": 1218812, "panel_aspectRatio": 1.8485221674876848, "category": "Method", "figures": 0, "textlen": 165, "fig_size": 0, "title": "Methods", "textRatio": 0.3340080971659919, "figRatio": 0.0}, "9": {"xy": [986, 1277, 1490, 1028], "panel_size": 1531720, "panel_aspectRatio": 1.4494163424124513, "category": "Result", "figures": 4, "textlen": 35, "fig_size": 1075486, "title": "Results", "10": {"fig_size": 276390, "fig_aspectRatio": 1.6048192771084338, "fig_size_poster": 0.4469798657718121}, "11": {"fig_size": 300875, "fig_aspectRatio": 1.7469879518072289, "fig_size_poster": 0.4865771812080537}, "12": {"fig_size": 294000, "fig_aspectRatio": 6.666666666666667, "fig_size_poster": 0.9395973154362416}, "13": {"fig_size": 204221, "fig_aspectRatio": 2.378839590443686, "fig_size_poster": 0.4677852348993289}, "textRatio": 0.0708502024291498, "figRatio": 1.0}, "15": {"xy": [2491, 461, 818, 898], "panel_size": 734564, "panel_aspectRatio": 0.910913140311804, "category": "Discussion", "figures": 0, "textlen": 94, "fig_size": 0, "title": "Discussion", "textRatio": 0.1902834008097166, "figRatio": 0.0}, "17": {"xy": [2504, 1374, 803, 359], "panel_size": 288277, "panel_aspectRatio": 2.2367688022284122, "category": "Discussion", "figures": 0, "textlen": 21, "fig_size": 0, "title": "Future Work", "textRatio": 0.04251012145748988, "figRatio": 0.0}}}