{"poster_size": 9366192, "doclen": 645, "figlen": 1110288, "section": {"1": {"xy": [334, 25, 2892, 133], "panel_size": 384636, "panel_aspectRatio": 21.74436090225564, "category": "Title", "figures": 0, "textlen": 0, "fig_size": 0, "title": "Predicting Results for Professional Basketball Using NBA API Data", "textRatio": 0.0, "figRatio": 0.0}, "2": {"xy": [48, 403, 850, 800], "panel_size": 680000, "panel_aspectRatio": 1.0625, "category": "Introduction", "figures": 0, "textlen": 93, "fig_size": 0, "title": "Objectives", "textRatio": 0.14418604651162792, "figRatio": 0.0}, "3": {"xy": [51, 1225, 847, 491], "panel_size": 415877, "panel_aspectRatio": 1.725050916496945, "category": "Introduction", "figures": 0, "textlen": 60, "fig_size": 0, "title": "Background", "textRatio": 0.09302325581395349, "figRatio": 0.0}, "4": {"xy": [48, 1733, 855, 449], "panel_size": 383895, "panel_aspectRatio": 1.9042316258351892, "category": "Introduction", "figures": 0, "textlen": 53, "fig_size": 0, "title": "Data", "textRatio": 0.08217054263565891, "figRatio": 0.0}, "5": {"xy": [48, 2197, 861, 383], "panel_size": 329763, "panel_aspectRatio": 2.248041775456919, "category": "Introduction", "figures": 0, "textlen": 32, "fig_size": 0, "title": "Features", "textRatio": 0.04961240310077519, "figRatio": 0.0}, "6": {"xy": [924, 400, 849, 416], "panel_size": 353184, "panel_aspectRatio": 2.0408653846153846, "category": "Introduction", "figures": 0, "textlen": 48, "fig_size": 0, "title": "Features", "textRatio": 0.07441860465116279, "figRatio": 0.0}, "7": {"xy": [921, 841, 855, 506], "panel_size": 432630, "panel_aspectRatio": 1.6897233201581028, "category": "Method", "figures": 0, "textlen": 40, "fig_size": 0, "title": "Models", "textRatio": 0.06201550387596899, "figRatio": 0.0}, "8": {"xy": [1792, 397, 836, 947], "panel_size": 791692, "panel_aspectRatio": 0.8827877507919747, "category": "Result", "figures": 0, "textlen": 131, "fig_size": 0, "title": "Results", "textRatio": 0.20310077519379846, "figRatio": 0.0}, "9": {"xy": [2670, 430, 886, 728], "panel_size": 645008, "panel_aspectRatio": 1.217032967032967, "category": "Result", "figures": 1, "textlen": 0, "fig_size": 580500, "title": "Results", "20": {"fig_size": 580500, "fig_aspectRatio": 1.2740740740740741, "fig_size_poster": 0.9706546275395034}, "textRatio": 0.0, "figRatio": 0.5228373178850892}, "10": {"xy": [920, 1372, 1697, 586], "panel_size": 994442, "panel_aspectRatio": 2.8959044368600684, "category": "Result", "figures": 1, "textlen": 0, "fig_size": 529788, "title": "Important Result", "21": {"fig_size": 529788, "fig_aspectRatio": 4.1568627450980395, "fig_size_poster": 0.8744843842074249}, "textRatio": 0.0, "figRatio": 0.47716268211491075}, "11": {"xy": [923, 1972, 1705, 446], "panel_size": 760430, "panel_aspectRatio": 3.8228699551569507, "category": "Discussion", "figures": 0, "textlen": 120, "fig_size": 0, "title": "Discussion", "textRatio": 0.18604651162790697, "figRatio": 0.0}, "12": {"xy": [2653, 1186, 873, 639], "panel_size": 557847, "panel_aspectRatio": 1.3661971830985915, "category": "Discussion", "figures": 0, "textlen": 68, "fig_size": 0, "title": "Future Work", "textRatio": 0.10542635658914729, "figRatio": 0.0}}}