{"poster_size": 4478976, "doclen": 346, "figlen": 1153628, "section": {"1": {"xy": [384, 34, 1851, 87], "panel_size": 161037, "panel_aspectRatio": 21.275862068965516, "category": "Title", "figures": 0, "textlen": 0, "fig_size": 0, "title": "Compositional Event Detection Using Weak Supervision", "textRatio": 0.0, "figRatio": 0.0}, "2": {"xy": [27, 271, 1370, 414], "panel_size": 567180, "panel_aspectRatio": 3.3091787439613527, "category": "Introduction", "figures": 0, "textlen": 115, "fig_size": 0, "title": "Abstract", "textRatio": 0.33236994219653176, "figRatio": 0.0}, "4": {"xy": [1406, 263, 1160, 97], "panel_size": 112520, "panel_aspectRatio": 11.958762886597938, "category": "Method", "figures": 0, "textlen": 20, "fig_size": 0, "title": "Dataset", "textRatio": 0.057803468208092484, "figRatio": 0.0}, "6": {"xy": [1404, 382, 1156, 296], "panel_size": 342176, "panel_aspectRatio": 3.9054054054054053, "category": "Method", "figures": 2, "textlen": 18, "fig_size": 170435, "title": "Task: Detecting Commercials", "7": {"fig_size": 82460, "fig_aspectRatio": 1.7511520737327189, "fig_size_poster": 0.328719723183391}, "10": {"fig_size": 87975, "fig_aspectRatio": 1.7377777777777779, "fig_size_poster": 0.3382352941176471}, "textRatio": 0.05202312138728324, "figRatio": 0.14773826571477114}, "11": {"xy": [29, 698, 2538, 509], "panel_size": 1291842, "panel_aspectRatio": 4.986247544204322, "category": "Method", "figures": 2, "textlen": 94, "fig_size": 612322, "title": "Deep Learning approach: ResNet-50 Model", "12": {"fig_size": 283318, "fig_aspectRatio": 1.6610169491525424, "fig_size_poster": 0.2702915681639086}, "14": {"fig_size": 329004, "fig_aspectRatio": 1.4220374220374221, "fig_size_poster": 0.2695035460992908}, "textRatio": 0.27167630057803466, "figRatio": 0.5307794193622207}, "15": {"xy": [29, 1225, 1375, 476], "panel_size": 654500, "panel_aspectRatio": 2.888655462184874, "category": "Method", "figures": 2, "textlen": 35, "fig_size": 370871, "title": "Classic ML: GDA versus SVM (RBF kernel)", "16": {"fig_size": 185785, "fig_aspectRatio": 1.3945205479452054, "fig_size_poster": 0.37018181818181817}, "18": {"fig_size": 185086, "fig_aspectRatio": 1.4441340782122905, "fig_size_poster": 0.376}, "textRatio": 0.10115606936416185, "figRatio": 0.3214823149230081}, "19": {"xy": [1415, 1223, 1152, 320], "panel_size": 368640, "panel_aspectRatio": 3.6, "category": "Discussion", "figures": 0, "textlen": 64, "fig_size": 0, "title": "Discussion and Future Work", "textRatio": 0.18497109826589594, "figRatio": 0.0}}}