{"poster_size": 4478976, "doclen": 481, "figlen": 738564, "section": {"1": {"xy": [464, 37, 1651, 79], "panel_size": 130429, "panel_aspectRatio": 20.89873417721519, "category": "Title", "figures": 0, "textlen": 0, "fig_size": 0, "title": "The Price is Right: Predicting Prices with Product Images", "textRatio": 0.0, "figRatio": 0.0}, "2": {"xy": [17, 296, 753, 400], "panel_size": 301200, "panel_aspectRatio": 1.8825, "category": "Introduction", "figures": 0, "textlen": 47, "fig_size": 0, "title": "Motivation", "textRatio": 0.09771309771309772, "figRatio": 0.0}, "4": {"xy": [23, 739, 754, 400], "panel_size": 301600, "panel_aspectRatio": 1.885, "category": "Introduction", "figures": 1, "textlen": 39, "fig_size": 101210, "title": "Datasets", "5": {"fig_size": 101210, "fig_aspectRatio": 4.813793103448276, "fig_size_poster": 0.9257294429708223}, "textRatio": 0.08108108108108109, "figRatio": 0.13703619456133795}, "7": {"xy": [17, 1169, 753, 535], "panel_size": 402855, "panel_aspectRatio": 1.4074766355140187, "category": "Method", "figures": 0, "textlen": 78, "fig_size": 0, "title": "Predictive Models", "textRatio": 0.16216216216216217, "figRatio": 0.0}, "9": {"xy": [787, 308, 1157, 470], "panel_size": 543790, "panel_aspectRatio": 2.4617021276595743, "category": "Method", "figures": 3, "textlen": 53, "fig_size": 170070, "title": "Evaluation", "10": {"fig_size": 58464, "fig_aspectRatio": 2.8194444444444446, "fig_size_poster": 0.3509075194468453}, "11": {"fig_size": 57266, "fig_aspectRatio": 3.051094890510949, "fig_size_poster": 0.3612791702679343}, "12": {"fig_size": 54340, "fig_aspectRatio": 3.2153846153846155, "fig_size_poster": 0.3612791702679343}, "textRatio": 0.1101871101871102, "figRatio": 0.23027117487448617}, "14": {"xy": [781, 794, 1167, 916], "panel_size": 1068972, "panel_aspectRatio": 1.2740174672489082, "category": "Result", "figures": 1, "textlen": 118, "fig_size": 467284, "title": "Visualization methods and results", "16": {"fig_size": 467284, "fig_aspectRatio": 0.7525380710659898, "fig_size_poster": 0.508140531276778}, "textRatio": 0.24532224532224534, "figRatio": 0.6326926305641759}, "17": {"xy": [1979, 314, 577, 488], "panel_size": 281576, "panel_aspectRatio": 1.1823770491803278, "category": "Result", "figures": 0, "textlen": 73, "fig_size": 0, "title": "Conlusion", "textRatio": 0.15176715176715178, "figRatio": 0.0}, "19": {"xy": [1968, 837, 607, 390], "panel_size": 236730, "panel_aspectRatio": 1.5564102564102564, "category": "Discussion", "figures": 0, "textlen": 73, "fig_size": 0, "title": "Future Work + Applications", "textRatio": 0.15176715176715178, "figRatio": 0.0}}}